exactBin/__init__.py
exactBin-0.0.3.dist-info/METADATA
exactBin-0.0.3.dist-info/WHEEL
exactBin-0.0.3.dist-info/top_level.txt
exactBin-0.0.3.dist-info/RECORD
