Metadata-Version: 2.1
Name: exactBin
Version: 0.0.3
Summary: A Python module for infinite precision binary floats and arithmetic.
